openms_insight/__init__.py
openms_insight/components/__init__.py
openms_insight/components/heatmap.py
openms_insight/components/lineplot.py
openms_insight/components/sequenceview.py
openms_insight/components/table.py
openms_insight/components/volcanoplot.py
openms_insight/core/__init__.py
openms_insight/core/base.py
openms_insight/core/cache.py
openms_insight/core/registry.py
openms_insight/core/state.py
openms_insight/core/subprocess_preprocess.py
openms_insight/preprocessing/__init__.py
openms_insight/preprocessing/compression.py
openms_insight/preprocessing/filtering.py
openms_insight/preprocessing/scatter.py
openms_insight/rendering/__init__.py
openms_insight/rendering/bridge.py
openms_insight/js-component/dist/index.html
openms_insight/js-component/dist/assets/index.css
openms_insight/js-component/dist/assets/index.js
openms_insight/js-component/dist/assets/materialdesignicons-webfont.eot
openms_insight/js-component/dist/assets/materialdesignicons-webfont.ttf
openms_insight/js-component/dist/assets/materialdesignicons-webfont.woff
openms_insight/js-component/dist/assets/materialdesignicons-webfont.woff2
openms_insight-0.1.6.dist-info/METADATA
openms_insight-0.1.6.dist-info/WHEEL
openms_insight-0.1.6.dist-info/licenses/LICENSE
openms_insight-0.1.6.dist-info/RECORD
