Metadata-Version: 2.4
Name: openms-insight
Version: 0.1.6
Summary: Interactive visualization components for mass spectrometry data in Streamlit
Project-URL: Homepage, https://github.com/t0mdavid-m/OpenMS-Insight
Project-URL: Documentation, https://github.com/t0mdavid-m/OpenMS-Insight#readme
Project-URL: Repository, https://github.com/t0mdavid-m/OpenMS-Insight
Project-URL: Issues, https://github.com/t0mdavid-m/OpenMS-Insight/issues
Author: Tom David Müller
License-Expression: BSD-3-Clause
License-File: LICENSE
Keywords: mass-spectrometry,openms,plotly,proteomics,streamlit,tabulator,visualization,vue
Classifier: Development Status :: 4 - Beta
Classifier: Intended Audience :: Developers
Classifier: Intended Audience :: Science/Research
Classifier: License :: OSI Approved :: BSD License
Classifier: Programming Language :: Python :: 3
Classifier: Programming Language :: Python :: 3.9
Classifier: Programming Language :: Python :: 3.10
Classifier: Programming Language :: Python :: 3.11
Classifier: Programming Language :: Python :: 3.12
Classifier: Topic :: Scientific/Engineering :: Bio-Informatics
Classifier: Topic :: Scientific/Engineering :: Visualization
Requires-Python: >=3.9
Requires-Dist: pandas>=1.5.0
Requires-Dist: polars>=0.19.0
Requires-Dist: streamlit>=1.20.0
Provides-Extra: dev
Requires-Dist: black>=23.0.0; extra == 'dev'
Requires-Dist: mypy>=1.0.0; extra == 'dev'
Requires-Dist: pytest-cov>=4.0.0; extra == 'dev'
Requires-Dist: pytest>=7.0.0; extra == 'dev'
Requires-Dist: ruff>=0.1.0; extra == 'dev'
